cshw_tweet_sentiment/__init__.py
cshw_tweet_sentiment/sentiment.py
cshw_tweet_sentiment-2.0.1.dist-info/METADATA
cshw_tweet_sentiment-2.0.1.dist-info/WHEEL
cshw_tweet_sentiment-2.0.1.dist-info/top_level.txt
cshw_tweet_sentiment-2.0.1.dist-info/RECORD
