Metadata-Version: 2.1
Name: cshw_tweet_sentiment
Version: 2.0.1
Summary: Tweet sentiment analysis
Author: Cameron Hyaes
Author-email: c.cash.hayes@gmail.com
Keywords: python
Classifier: Development Status :: 3 - Alpha
Classifier: Intended Audience :: Education
Classifier: Programming Language :: Python :: 2
Classifier: Programming Language :: Python :: 3
Classifier: Operating System :: MacOS :: MacOS X
Classifier: Operating System :: Microsoft :: Windows
